threadArt/__init__.py
threadArt/polar_system.py
threadArt/thread_art.py
threadArt/visualizer.py
threadArt-1.2.0.dist-info/METADATA
threadArt-1.2.0.dist-info/WHEEL
threadArt-1.2.0.dist-info/top_level.txt
threadArt-1.2.0.dist-info/RECORD
