Metadata-Version: 2.1
Name: threadArt
Version: 1.2.0
Summary: A python module for generating thread art sequences.
Home-page: https://github.com/quintindunn/threadArt
Author: Quintin Dunn
Author-email: dunnquintin07@gmail.com
License: MIT
Keywords: art,string art,thread art
Classifier: Development Status :: 5 - Production/Stable
Classifier: Operating System :: Microsoft :: Windows :: Windows 10
Classifier: Programming Language :: Python :: 3
Requires-Dist: numpy
Requires-Dist: opencv-python
